setup.py
applause/__init__.py
applause.egg-info/PKG-INFO
applause.egg-info/SOURCES.txt
applause.egg-info/dependency_links.txt
applause.egg-info/entry_points.txt
applause.egg-info/not-zip-safe
applause.egg-info/requires.txt
applause.egg-info/top_level.txt