Metadata-Version: 1.0
Name: applause
Version: 0.1
Summary: Applaud closing bugs.
Home-page: http://github.com/storborg/applause
Author: Scott Torborg
Author-email: scott@cartlogic.com
License: MIT
Keywords: git github stats dashboard issues bug tracker
Platform: UNKNOWN
Classifier: License :: OSI Approved :: MIT License
Classifier: Programming Language :: Python :: 2.7
